LICENSE.txt
README.md
setup.py
sama/__init__.py
sama/client.py
sama.egg-info/PKG-INFO
sama.egg-info/SOURCES.txt
sama.egg-info/dependency_links.txt
sama.egg-info/requires.txt
sama.egg-info/top_level.txt
sama/constants/__init__.py
sama/constants/tasks.py
sama/databricks/__init__.py
sama/databricks/client.py
tests/test_client.py