Metadata-Version: 2.1
Name: sama
Version: 0.5.11
Summary: Sama Python Client and Databricks Connector
Home-page: https://www.sama.com
Author: Edward
Author-email: echan@samasource.org
License:  Apache-2.0 license
License-File: LICENSE.txt
